ctao_sphinx_theme/__init__.py
ctao_sphinx_theme/__main__.py
ctao_sphinx_theme/_version.py
ctao_sphinx_theme/theme.toml
ctao_sphinx_theme/ctao-logos/ctao.png
ctao_sphinx_theme/ctao-logos/ctao_acada.png
ctao_sphinx_theme/ctao-logos/ctao_acada_reversed.png
ctao_sphinx_theme/ctao-logos/ctao_afc.png
ctao_sphinx_theme/ctao-logos/ctao_afc_reversed.png
ctao_sphinx_theme/ctao-logos/ctao_australia.png
ctao_sphinx_theme/ctao-logos/ctao_australia_reversed.png
ctao_sphinx_theme/ctao-logos/ctao_austria.png
ctao_sphinx_theme/ctao-logos/ctao_austria_reversed.png
ctao_sphinx_theme/ctao-logos/ctao_brazil.png
ctao_sphinx_theme/ctao-logos/ctao_brazil_reversed.png
ctao_sphinx_theme/ctao-logos/ctao_chile.png
ctao_sphinx_theme/ctao-logos/ctao_chile_reversed.png
ctao_sphinx_theme/ctao-logos/ctao_consortium.png
ctao_sphinx_theme/ctao-logos/ctao_consortium_reversed.png
ctao_sphinx_theme/ctao-logos/ctao_croatia.png
ctao_sphinx_theme/ctao-logos/ctao_croatia_reversed.png
ctao_sphinx_theme/ctao-logos/ctao_czechrepublic.png
ctao_sphinx_theme/ctao-logos/ctao_czechrepublic_reversed.png
ctao_sphinx_theme/ctao-logos/ctao_finland.png
ctao_sphinx_theme/ctao-logos/ctao_finland_reversed.png
ctao_sphinx_theme/ctao-logos/ctao_france.png
ctao_sphinx_theme/ctao-logos/ctao_france_reversed.png
ctao_sphinx_theme/ctao-logos/ctao_germany.png
ctao_sphinx_theme/ctao-logos/ctao_germany_reversed.png
ctao_sphinx_theme/ctao-logos/ctao_ikcreviewcommittee.png
ctao_sphinx_theme/ctao-logos/ctao_ikcreviewcommittee_reversed.png
ctao_sphinx_theme/ctao-logos/ctao_india.png
ctao_sphinx_theme/ctao-logos/ctao_india_reversed.png
ctao_sphinx_theme/ctao-logos/ctao_ireland.png
ctao_sphinx_theme/ctao-logos/ctao_ireland_reversed.png
ctao_sphinx_theme/ctao-logos/ctao_italy.png
ctao_sphinx_theme/ctao-logos/ctao_italy_reversed.png
ctao_sphinx_theme/ctao-logos/ctao_japan.png
ctao_sphinx_theme/ctao-logos/ctao_japan_reversed.png
ctao_sphinx_theme/ctao-logos/ctao_lst.png
ctao_sphinx_theme/ctao-logos/ctao_lst_reversed.png
ctao_sphinx_theme-0.1.5.dist-info/METADATA
ctao_sphinx_theme-0.1.5.dist-info/WHEEL
ctao_sphinx_theme-0.1.5.dist-info/entry_points.txt
ctao_sphinx_theme-0.1.5.dist-info/top_level.txt
ctao_sphinx_theme-0.1.5.dist-info/RECORD
